notion/__init__.py
notion/block.py
notion/client.py
notion/collection.py
notion/logger.py
notion/maps.py
notion/markdown.py
notion/monitor.py
notion/operations.py
notion/records.py
notion/settings.py
notion/smoke_test.py
notion/space.py
notion/store.py
notion/user.py
notion/utils.py
notion-0.0.25.dist-info/LICENSE
notion-0.0.25.dist-info/METADATA
notion-0.0.25.dist-info/WHEEL
notion-0.0.25.dist-info/top_level.txt
notion-0.0.25.dist-info/RECORD
