Metadata-Version: 2.1
Name: notion
Version: 0.0.25
Summary: Unofficial Python API client for Notion.so
Home-page: https://github.com/jamalex/notion-py
Author: Jamie Alexandre
Author-email: jamalex+python@gmail.com
License: UNKNOWN
Platform: UNKNOWN
Classifier: Programming Language :: Python :: 3
Classifier: License :: OSI Approved :: MIT License
Classifier: Operating System :: OS Independent
Requires-Python: >=3.5
